allen_powerplatform_client/__init__.py
allen_powerplatform_client/api_client.py
allen_powerplatform_client/api_response.py
allen_powerplatform_client/configuration.py
allen_powerplatform_client/exceptions.py
allen_powerplatform_client/py.typed
allen_powerplatform_client/rest.py
allen_powerplatform_client/api/__init__.py
allen_powerplatform_client/api/default_api.py
allen_powerplatform_client/models/__init__.py
allen_powerplatform_client/models/get_table_request.py
allen_powerplatform_client/models/post_baseline_weight_request.py
allen_powerplatform_client/models/post_water_record_request.py
allen_powerplatform_client/models/post_weight_record_request.py
allen_powerplatform_client-0.1.2.dist-info/METADATA
allen_powerplatform_client-0.1.2.dist-info/WHEEL
allen_powerplatform_client-0.1.2.dist-info/top_level.txt
allen_powerplatform_client-0.1.2.dist-info/RECORD
